do.py
do_runner-0.1.3.dist-info/METADATA
do_runner-0.1.3.dist-info/WHEEL
do_runner-0.1.3.dist-info/entry_points.txt
do_runner-0.1.3.dist-info/licenses/LICENSE.txt
do_runner-0.1.3.dist-info/RECORD
