Metadata-Version: 2.4
Name: do-runner
Version: 0.1.3
Summary: Simple just- and xc-like task runner.
Project-URL: Repository, https://codeberg.org/cgranade/do
Author-email: Cassandra Granade <cgranade@cgranade.com>
License: MIT
License-File: LICENSE.txt
Requires-Python: >=3.13
Requires-Dist: markdown-it-py
Requires-Dist: rich
